{
  "version": "xfd-20260528021800",
  "forecast": [
    {
      "date": "2026-05-28",
      "yhat": 5.7933,
      "yhat_lower": 5.2765,
      "yhat_upper": 6.3101,
      "confidence": 0.52,
      "trend": "flat"
    },
    {
      "date": "2026-05-29",
      "yhat": 7.8998,
      "yhat_lower": 7.1951,
      "yhat_upper": 8.6045,
      "confidence": 0.52,
      "trend": "up"
    },
    {
      "date": "2026-05-30",
      "yhat": 7.9124,
      "yhat_lower": 7.2066,
      "yhat_upper": 8.6182,
      "confidence": 0.52,
      "trend": "flat"
    },
    {
      "date": "2026-05-31",
      "yhat": 5.83,
      "yhat_lower": 5.3099,
      "yhat_upper": 6.35,
      "confidence": 0.52,
      "trend": "down"
    },
    {
      "date": "2026-06-01",
      "yhat": 4.8021,
      "yhat_lower": 4.3738,
      "yhat_upper": 5.2305,
      "confidence": 0.52,
      "trend": "down"
    },
    {
      "date": "2026-06-02",
      "yhat": 8.9351,
      "yhat_lower": 8.1381,
      "yhat_upper": 9.7322,
      "confidence": 0.52,
      "trend": "up"
    },
    {
      "date": "2026-06-03",
      "yhat": 4.8414,
      "yhat_lower": 4.4095,
      "yhat_upper": 5.2732,
      "confidence": 0.52,
      "trend": "down"
    },
    {
      "date": "2026-06-04",
      "yhat": 5.8888,
      "yhat_lower": 5.3635,
      "yhat_upper": 6.4141,
      "confidence": 0.52,
      "trend": "up"
    },
    {
      "date": "2026-06-05",
      "yhat": 7.9953,
      "yhat_lower": 7.2821,
      "yhat_upper": 8.7085,
      "confidence": 0.52,
      "trend": "up"
    },
    {
      "date": "2026-06-06",
      "yhat": 8.0079,
      "yhat_lower": 7.2936,
      "yhat_upper": 8.7222,
      "confidence": 0.52,
      "trend": "flat"
    },
    {
      "date": "2026-06-07",
      "yhat": 5.9255,
      "yhat_lower": 5.3969,
      "yhat_upper": 6.454,
      "confidence": 0.52,
      "trend": "down"
    },
    {
      "date": "2026-06-08",
      "yhat": 4.8976,
      "yhat_lower": 4.4608,
      "yhat_upper": 5.3345,
      "confidence": 0.52,
      "trend": "down"
    },
    {
      "date": "2026-06-09",
      "yhat": 9.0307,
      "yhat_lower": 8.2251,
      "yhat_upper": 9.8362,
      "confidence": 0.52,
      "trend": "up"
    },
    {
      "date": "2026-06-10",
      "yhat": 4.9369,
      "yhat_lower": 4.4965,
      "yhat_upper": 5.3773,
      "confidence": 0.52,
      "trend": "down"
    },
    {
      "date": "2026-06-11",
      "yhat": 5.9843,
      "yhat_lower": 5.4505,
      "yhat_upper": 6.5181,
      "confidence": 0.52,
      "trend": "up"
    },
    {
      "date": "2026-06-12",
      "yhat": 8.0908,
      "yhat_lower": 7.3691,
      "yhat_upper": 8.8125,
      "confidence": 0.52,
      "trend": "up"
    },
    {
      "date": "2026-06-13",
      "yhat": 8.1034,
      "yhat_lower": 7.3806,
      "yhat_upper": 8.8262,
      "confidence": 0.52,
      "trend": "flat"
    },
    {
      "date": "2026-06-14",
      "yhat": 6.021,
      "yhat_lower": 5.4839,
      "yhat_upper": 6.558,
      "confidence": 0.52,
      "trend": "down"
    },
    {
      "date": "2026-06-15",
      "yhat": 4.9932,
      "yhat_lower": 4.5478,
      "yhat_upper": 5.4385,
      "confidence": 0.52,
      "trend": "down"
    },
    {
      "date": "2026-06-16",
      "yhat": 9.1262,
      "yhat_lower": 8.3121,
      "yhat_upper": 9.9402,
      "confidence": 0.52,
      "trend": "up"
    },
    {
      "date": "2026-06-17",
      "yhat": 5.0324,
      "yhat_lower": 4.5835,
      "yhat_upper": 5.4813,
      "confidence": 0.52,
      "trend": "down"
    },
    {
      "date": "2026-06-18",
      "yhat": 6.0798,
      "yhat_lower": 5.5375,
      "yhat_upper": 6.6222,
      "confidence": 0.52,
      "trend": "up"
    },
    {
      "date": "2026-06-19",
      "yhat": 8.1863,
      "yhat_lower": 7.4561,
      "yhat_upper": 8.9166,
      "confidence": 0.52,
      "trend": "up"
    },
    {
      "date": "2026-06-20",
      "yhat": 8.1989,
      "yhat_lower": 7.4676,
      "yhat_upper": 8.9302,
      "confidence": 0.52,
      "trend": "flat"
    },
    {
      "date": "2026-06-21",
      "yhat": 6.1165,
      "yhat_lower": 5.5709,
      "yhat_upper": 6.6621,
      "confidence": 0.52,
      "trend": "down"
    },
    {
      "date": "2026-06-22",
      "yhat": 5.0887,
      "yhat_lower": 4.6348,
      "yhat_upper": 5.5426,
      "confidence": 0.52,
      "trend": "down"
    },
    {
      "date": "2026-06-23",
      "yhat": 9.2217,
      "yhat_lower": 8.3991,
      "yhat_upper": 10.0442,
      "confidence": 0.52,
      "trend": "up"
    },
    {
      "date": "2026-06-24",
      "yhat": 5.1279,
      "yhat_lower": 4.6705,
      "yhat_upper": 5.5853,
      "confidence": 0.52,
      "trend": "down"
    },
    {
      "date": "2026-06-25",
      "yhat": 6.1753,
      "yhat_lower": 5.6245,
      "yhat_upper": 6.7262,
      "confidence": 0.52,
      "trend": "up"
    },
    {
      "date": "2026-06-26",
      "yhat": 8.2818,
      "yhat_lower": 7.5431,
      "yhat_upper": 9.0206,
      "confidence": 0.52,
      "trend": "up"
    }
  ]
}