{
  "version": "xfd-20260525032649",
  "forecast": [
    {
      "date": "2026-05-25",
      "yhat": 49.04,
      "yhat_lower": 45.3322,
      "yhat_upper": 52.7478,
      "confidence": 0.8598,
      "trend": "flat"
    },
    {
      "date": "2026-05-26",
      "yhat": 49.0547,
      "yhat_lower": 45.3457,
      "yhat_upper": 52.7636,
      "confidence": 0.8598,
      "trend": "flat"
    },
    {
      "date": "2026-05-27",
      "yhat": 49.0619,
      "yhat_lower": 45.3524,
      "yhat_upper": 52.7714,
      "confidence": 0.8598,
      "trend": "flat"
    },
    {
      "date": "2026-05-28",
      "yhat": 49.0673,
      "yhat_lower": 45.3574,
      "yhat_upper": 52.7771,
      "confidence": 0.8598,
      "trend": "flat"
    },
    {
      "date": "2026-05-29",
      "yhat": 49.0725,
      "yhat_lower": 45.3622,
      "yhat_upper": 52.7828,
      "confidence": 0.8598,
      "trend": "flat"
    },
    {
      "date": "2026-05-30",
      "yhat": 49.0782,
      "yhat_lower": 45.3675,
      "yhat_upper": 52.7889,
      "confidence": 0.8598,
      "trend": "flat"
    },
    {
      "date": "2026-05-31",
      "yhat": 49.0847,
      "yhat_lower": 45.3735,
      "yhat_upper": 52.7959,
      "confidence": 0.8598,
      "trend": "flat"
    },
    {
      "date": "2026-06-01",
      "yhat": 49.078,
      "yhat_lower": 45.3673,
      "yhat_upper": 52.7887,
      "confidence": 0.8598,
      "trend": "flat"
    },
    {
      "date": "2026-06-02",
      "yhat": 49.0721,
      "yhat_lower": 45.3619,
      "yhat_upper": 52.7824,
      "confidence": 0.8598,
      "trend": "flat"
    },
    {
      "date": "2026-06-03",
      "yhat": 49.0675,
      "yhat_lower": 45.3576,
      "yhat_upper": 52.7774,
      "confidence": 0.8598,
      "trend": "flat"
    },
    {
      "date": "2026-06-04",
      "yhat": 49.0629,
      "yhat_lower": 45.3534,
      "yhat_upper": 52.7725,
      "confidence": 0.8598,
      "trend": "flat"
    },
    {
      "date": "2026-06-05",
      "yhat": 49.0576,
      "yhat_lower": 45.3485,
      "yhat_upper": 52.7668,
      "confidence": 0.8598,
      "trend": "flat"
    },
    {
      "date": "2026-06-06",
      "yhat": 49.051,
      "yhat_lower": 45.3423,
      "yhat_upper": 52.7596,
      "confidence": 0.8598,
      "trend": "flat"
    },
    {
      "date": "2026-06-07",
      "yhat": 49.0459,
      "yhat_lower": 45.3376,
      "yhat_upper": 52.7542,
      "confidence": 0.8598,
      "trend": "flat"
    },
    {
      "date": "2026-06-08",
      "yhat": 49.045,
      "yhat_lower": 45.3368,
      "yhat_upper": 52.7531,
      "confidence": 0.8598,
      "trend": "flat"
    },
    {
      "date": "2026-06-09",
      "yhat": 49.0447,
      "yhat_lower": 45.3366,
      "yhat_upper": 52.7529,
      "confidence": 0.8598,
      "trend": "flat"
    },
    {
      "date": "2026-06-10",
      "yhat": 49.0444,
      "yhat_lower": 45.3363,
      "yhat_upper": 52.7526,
      "confidence": 0.8598,
      "trend": "flat"
    },
    {
      "date": "2026-06-11",
      "yhat": 49.0442,
      "yhat_lower": 45.336,
      "yhat_upper": 52.7523,
      "confidence": 0.8598,
      "trend": "flat"
    },
    {
      "date": "2026-06-12",
      "yhat": 49.0444,
      "yhat_lower": 45.3363,
      "yhat_upper": 52.7526,
      "confidence": 0.8598,
      "trend": "flat"
    },
    {
      "date": "2026-06-13",
      "yhat": 49.0456,
      "yhat_lower": 45.3373,
      "yhat_upper": 52.7538,
      "confidence": 0.8598,
      "trend": "flat"
    },
    {
      "date": "2026-06-14",
      "yhat": 49.047,
      "yhat_lower": 45.3386,
      "yhat_upper": 52.7553,
      "confidence": 0.8598,
      "trend": "flat"
    },
    {
      "date": "2026-06-15",
      "yhat": 49.0474,
      "yhat_lower": 45.339,
      "yhat_upper": 52.7557,
      "confidence": 0.8598,
      "trend": "flat"
    },
    {
      "date": "2026-06-16",
      "yhat": 49.0474,
      "yhat_lower": 45.339,
      "yhat_upper": 52.7558,
      "confidence": 0.8598,
      "trend": "flat"
    },
    {
      "date": "2026-06-17",
      "yhat": 49.0475,
      "yhat_lower": 45.3391,
      "yhat_upper": 52.7559,
      "confidence": 0.8598,
      "trend": "flat"
    },
    {
      "date": "2026-06-18",
      "yhat": 49.0477,
      "yhat_lower": 45.3393,
      "yhat_upper": 52.7561,
      "confidence": 0.8598,
      "trend": "flat"
    },
    {
      "date": "2026-06-19",
      "yhat": 49.048,
      "yhat_lower": 45.3396,
      "yhat_upper": 52.7564,
      "confidence": 0.8598,
      "trend": "flat"
    },
    {
      "date": "2026-06-20",
      "yhat": 49.048,
      "yhat_lower": 45.3396,
      "yhat_upper": 52.7565,
      "confidence": 0.8598,
      "trend": "flat"
    },
    {
      "date": "2026-06-21",
      "yhat": 49.048,
      "yhat_lower": 45.3396,
      "yhat_upper": 52.7564,
      "confidence": 0.8598,
      "trend": "flat"
    },
    {
      "date": "2026-06-22",
      "yhat": 49.0483,
      "yhat_lower": 45.3398,
      "yhat_upper": 52.7567,
      "confidence": 0.8598,
      "trend": "flat"
    },
    {
      "date": "2026-06-23",
      "yhat": 49.0488,
      "yhat_lower": 45.3403,
      "yhat_upper": 52.7573,
      "confidence": 0.8598,
      "trend": "flat"
    }
  ]
}