{
  "version": "xfd-20260526093219",
  "forecast": [
    {
      "date": "2026-05-27",
      "yhat": 24.9532,
      "yhat_lower": 23.0464,
      "yhat_upper": 26.8599,
      "confidence": 0.8396,
      "trend": "flat"
    },
    {
      "date": "2026-05-28",
      "yhat": 24.962,
      "yhat_lower": 23.0545,
      "yhat_upper": 26.8694,
      "confidence": 0.8396,
      "trend": "flat"
    },
    {
      "date": "2026-05-29",
      "yhat": 24.9815,
      "yhat_lower": 23.0725,
      "yhat_upper": 26.8904,
      "confidence": 0.8396,
      "trend": "flat"
    },
    {
      "date": "2026-05-30",
      "yhat": 24.971,
      "yhat_lower": 23.0629,
      "yhat_upper": 26.8791,
      "confidence": 0.8396,
      "trend": "flat"
    },
    {
      "date": "2026-05-31",
      "yhat": 24.9841,
      "yhat_lower": 23.0749,
      "yhat_upper": 26.8932,
      "confidence": 0.8396,
      "trend": "flat"
    },
    {
      "date": "2026-06-01",
      "yhat": 25.0986,
      "yhat_lower": 23.1807,
      "yhat_upper": 27.0165,
      "confidence": 0.8396,
      "trend": "flat"
    },
    {
      "date": "2026-06-02",
      "yhat": 25.0614,
      "yhat_lower": 23.1463,
      "yhat_upper": 26.9764,
      "confidence": 0.8396,
      "trend": "flat"
    },
    {
      "date": "2026-06-03",
      "yhat": 25.0047,
      "yhat_lower": 23.094,
      "yhat_upper": 26.9155,
      "confidence": 0.8396,
      "trend": "flat"
    },
    {
      "date": "2026-06-04",
      "yhat": 25.0136,
      "yhat_lower": 23.1022,
      "yhat_upper": 26.9249,
      "confidence": 0.8396,
      "trend": "flat"
    },
    {
      "date": "2026-06-05",
      "yhat": 25.0331,
      "yhat_lower": 23.1202,
      "yhat_upper": 26.9459,
      "confidence": 0.8396,
      "trend": "flat"
    },
    {
      "date": "2026-06-06",
      "yhat": 25.0226,
      "yhat_lower": 23.1105,
      "yhat_upper": 26.9347,
      "confidence": 0.8396,
      "trend": "flat"
    },
    {
      "date": "2026-06-07",
      "yhat": 25.0357,
      "yhat_lower": 23.1226,
      "yhat_upper": 26.9487,
      "confidence": 0.8396,
      "trend": "flat"
    },
    {
      "date": "2026-06-08",
      "yhat": 25.1502,
      "yhat_lower": 23.2283,
      "yhat_upper": 27.072,
      "confidence": 0.8396,
      "trend": "flat"
    },
    {
      "date": "2026-06-09",
      "yhat": 25.113,
      "yhat_lower": 23.194,
      "yhat_upper": 27.032,
      "confidence": 0.8396,
      "trend": "flat"
    },
    {
      "date": "2026-06-10",
      "yhat": 25.0563,
      "yhat_lower": 23.1416,
      "yhat_upper": 26.971,
      "confidence": 0.8396,
      "trend": "flat"
    },
    {
      "date": "2026-06-11",
      "yhat": 25.0651,
      "yhat_lower": 23.1498,
      "yhat_upper": 26.9805,
      "confidence": 0.8396,
      "trend": "flat"
    },
    {
      "date": "2026-06-12",
      "yhat": 25.0846,
      "yhat_lower": 23.1678,
      "yhat_upper": 27.0015,
      "confidence": 0.8396,
      "trend": "flat"
    },
    {
      "date": "2026-06-13",
      "yhat": 25.0741,
      "yhat_lower": 23.1581,
      "yhat_upper": 26.9902,
      "confidence": 0.8396,
      "trend": "flat"
    },
    {
      "date": "2026-06-14",
      "yhat": 25.0872,
      "yhat_lower": 23.1702,
      "yhat_upper": 27.0042,
      "confidence": 0.8396,
      "trend": "flat"
    },
    {
      "date": "2026-06-15",
      "yhat": 25.2017,
      "yhat_lower": 23.276,
      "yhat_upper": 27.1275,
      "confidence": 0.8396,
      "trend": "flat"
    },
    {
      "date": "2026-06-16",
      "yhat": 25.1645,
      "yhat_lower": 23.2416,
      "yhat_upper": 27.0875,
      "confidence": 0.8396,
      "trend": "flat"
    },
    {
      "date": "2026-06-17",
      "yhat": 25.1079,
      "yhat_lower": 23.1893,
      "yhat_upper": 27.0265,
      "confidence": 0.8396,
      "trend": "flat"
    },
    {
      "date": "2026-06-18",
      "yhat": 25.1167,
      "yhat_lower": 23.1974,
      "yhat_upper": 27.036,
      "confidence": 0.8396,
      "trend": "flat"
    },
    {
      "date": "2026-06-19",
      "yhat": 25.1362,
      "yhat_lower": 23.2154,
      "yhat_upper": 27.057,
      "confidence": 0.8396,
      "trend": "flat"
    },
    {
      "date": "2026-06-20",
      "yhat": 25.1257,
      "yhat_lower": 23.2057,
      "yhat_upper": 27.0457,
      "confidence": 0.8396,
      "trend": "flat"
    },
    {
      "date": "2026-06-21",
      "yhat": 25.1388,
      "yhat_lower": 23.2178,
      "yhat_upper": 27.0598,
      "confidence": 0.8396,
      "trend": "flat"
    },
    {
      "date": "2026-06-22",
      "yhat": 25.2533,
      "yhat_lower": 23.3236,
      "yhat_upper": 27.183,
      "confidence": 0.8396,
      "trend": "flat"
    },
    {
      "date": "2026-06-23",
      "yhat": 25.2161,
      "yhat_lower": 23.2892,
      "yhat_upper": 27.143,
      "confidence": 0.8396,
      "trend": "flat"
    },
    {
      "date": "2026-06-24",
      "yhat": 25.1594,
      "yhat_lower": 23.2369,
      "yhat_upper": 27.082,
      "confidence": 0.8396,
      "trend": "flat"
    },
    {
      "date": "2026-06-25",
      "yhat": 25.1683,
      "yhat_lower": 23.245,
      "yhat_upper": 27.0915,
      "confidence": 0.8396,
      "trend": "flat"
    }
  ]
}