{
  "version": "xfd-20260528021724",
  "forecast": [
    {
      "date": "2026-05-28",
      "yhat": 12.3245,
      "yhat_lower": 11.3924,
      "yhat_upper": 13.2565,
      "confidence": 0.8593,
      "trend": "flat"
    },
    {
      "date": "2026-05-29",
      "yhat": 12.3346,
      "yhat_lower": 11.4018,
      "yhat_upper": 13.2675,
      "confidence": 0.8593,
      "trend": "flat"
    },
    {
      "date": "2026-05-30",
      "yhat": 12.3234,
      "yhat_lower": 11.3915,
      "yhat_upper": 13.2554,
      "confidence": 0.8593,
      "trend": "flat"
    },
    {
      "date": "2026-05-31",
      "yhat": 12.3037,
      "yhat_lower": 11.3732,
      "yhat_upper": 13.2342,
      "confidence": 0.8593,
      "trend": "flat"
    },
    {
      "date": "2026-06-01",
      "yhat": 12.3659,
      "yhat_lower": 11.4307,
      "yhat_upper": 13.3011,
      "confidence": 0.8593,
      "trend": "flat"
    },
    {
      "date": "2026-06-02",
      "yhat": 12.3941,
      "yhat_lower": 11.4568,
      "yhat_upper": 13.3314,
      "confidence": 0.8593,
      "trend": "flat"
    },
    {
      "date": "2026-06-03",
      "yhat": 12.4131,
      "yhat_lower": 11.4743,
      "yhat_upper": 13.3518,
      "confidence": 0.8593,
      "trend": "flat"
    },
    {
      "date": "2026-06-04",
      "yhat": 12.4025,
      "yhat_lower": 11.4645,
      "yhat_upper": 13.3404,
      "confidence": 0.8593,
      "trend": "flat"
    },
    {
      "date": "2026-06-05",
      "yhat": 12.398,
      "yhat_lower": 11.4604,
      "yhat_upper": 13.3356,
      "confidence": 0.8593,
      "trend": "flat"
    },
    {
      "date": "2026-06-06",
      "yhat": 12.4021,
      "yhat_lower": 11.4641,
      "yhat_upper": 13.34,
      "confidence": 0.8593,
      "trend": "flat"
    },
    {
      "date": "2026-06-07",
      "yhat": 12.414,
      "yhat_lower": 11.4752,
      "yhat_upper": 13.3529,
      "confidence": 0.8593,
      "trend": "flat"
    },
    {
      "date": "2026-06-08",
      "yhat": 12.4024,
      "yhat_lower": 11.4644,
      "yhat_upper": 13.3403,
      "confidence": 0.8593,
      "trend": "flat"
    },
    {
      "date": "2026-06-09",
      "yhat": 12.3943,
      "yhat_lower": 11.4569,
      "yhat_upper": 13.3316,
      "confidence": 0.8593,
      "trend": "flat"
    },
    {
      "date": "2026-06-10",
      "yhat": 12.3879,
      "yhat_lower": 11.451,
      "yhat_upper": 13.3248,
      "confidence": 0.8593,
      "trend": "flat"
    },
    {
      "date": "2026-06-11",
      "yhat": 12.3904,
      "yhat_lower": 11.4534,
      "yhat_upper": 13.3275,
      "confidence": 0.8593,
      "trend": "flat"
    },
    {
      "date": "2026-06-12",
      "yhat": 12.3934,
      "yhat_lower": 11.4561,
      "yhat_upper": 13.3307,
      "confidence": 0.8593,
      "trend": "flat"
    },
    {
      "date": "2026-06-13",
      "yhat": 12.3932,
      "yhat_lower": 11.456,
      "yhat_upper": 13.3305,
      "confidence": 0.8593,
      "trend": "flat"
    },
    {
      "date": "2026-06-14",
      "yhat": 12.3891,
      "yhat_lower": 11.4522,
      "yhat_upper": 13.3261,
      "confidence": 0.8593,
      "trend": "flat"
    },
    {
      "date": "2026-06-15",
      "yhat": 12.3911,
      "yhat_lower": 11.454,
      "yhat_upper": 13.3282,
      "confidence": 0.8593,
      "trend": "flat"
    },
    {
      "date": "2026-06-16",
      "yhat": 12.3936,
      "yhat_lower": 11.4563,
      "yhat_upper": 13.3309,
      "confidence": 0.8593,
      "trend": "flat"
    },
    {
      "date": "2026-06-17",
      "yhat": 12.3959,
      "yhat_lower": 11.4585,
      "yhat_upper": 13.3334,
      "confidence": 0.8593,
      "trend": "flat"
    },
    {
      "date": "2026-06-18",
      "yhat": 12.3954,
      "yhat_lower": 11.458,
      "yhat_upper": 13.3328,
      "confidence": 0.8593,
      "trend": "flat"
    },
    {
      "date": "2026-06-19",
      "yhat": 12.3937,
      "yhat_lower": 11.4564,
      "yhat_upper": 13.331,
      "confidence": 0.8593,
      "trend": "flat"
    },
    {
      "date": "2026-06-20",
      "yhat": 12.3924,
      "yhat_lower": 11.4552,
      "yhat_upper": 13.3296,
      "confidence": 0.8593,
      "trend": "flat"
    },
    {
      "date": "2026-06-21",
      "yhat": 12.3923,
      "yhat_lower": 11.4551,
      "yhat_upper": 13.3295,
      "confidence": 0.8593,
      "trend": "flat"
    },
    {
      "date": "2026-06-22",
      "yhat": 12.3907,
      "yhat_lower": 11.4536,
      "yhat_upper": 13.3278,
      "confidence": 0.8593,
      "trend": "flat"
    },
    {
      "date": "2026-06-23",
      "yhat": 12.3882,
      "yhat_lower": 11.4513,
      "yhat_upper": 13.3251,
      "confidence": 0.8593,
      "trend": "flat"
    },
    {
      "date": "2026-06-24",
      "yhat": 12.3853,
      "yhat_lower": 11.4486,
      "yhat_upper": 13.3219,
      "confidence": 0.8593,
      "trend": "flat"
    },
    {
      "date": "2026-06-25",
      "yhat": 12.3845,
      "yhat_lower": 11.4479,
      "yhat_upper": 13.3211,
      "confidence": 0.8593,
      "trend": "flat"
    },
    {
      "date": "2026-06-26",
      "yhat": 12.3849,
      "yhat_lower": 11.4482,
      "yhat_upper": 13.3215,
      "confidence": 0.8593,
      "trend": "flat"
    }
  ]
}