{
  "version": "xfd-20260526020412",
  "forecast": [
    {
      "date": "2026-05-26",
      "yhat": 2.3512,
      "yhat_lower": 2.1713,
      "yhat_upper": 2.5311,
      "confidence": 0.8375,
      "trend": "flat"
    },
    {
      "date": "2026-05-27",
      "yhat": 2.3628,
      "yhat_lower": 2.182,
      "yhat_upper": 2.5436,
      "confidence": 0.8375,
      "trend": "flat"
    },
    {
      "date": "2026-05-28",
      "yhat": 2.3567,
      "yhat_lower": 2.1764,
      "yhat_upper": 2.537,
      "confidence": 0.8375,
      "trend": "flat"
    },
    {
      "date": "2026-05-29",
      "yhat": 2.3449,
      "yhat_lower": 2.1656,
      "yhat_upper": 2.5243,
      "confidence": 0.8375,
      "trend": "flat"
    },
    {
      "date": "2026-05-30",
      "yhat": 2.3389,
      "yhat_lower": 2.16,
      "yhat_upper": 2.5178,
      "confidence": 0.8375,
      "trend": "flat"
    },
    {
      "date": "2026-05-31",
      "yhat": 2.3335,
      "yhat_lower": 2.155,
      "yhat_upper": 2.512,
      "confidence": 0.8375,
      "trend": "flat"
    },
    {
      "date": "2026-06-01",
      "yhat": 2.3403,
      "yhat_lower": 2.1613,
      "yhat_upper": 2.5193,
      "confidence": 0.8375,
      "trend": "flat"
    },
    {
      "date": "2026-06-02",
      "yhat": 2.3337,
      "yhat_lower": 2.1552,
      "yhat_upper": 2.5122,
      "confidence": 0.8375,
      "trend": "flat"
    },
    {
      "date": "2026-06-03",
      "yhat": 2.3453,
      "yhat_lower": 2.1659,
      "yhat_upper": 2.5247,
      "confidence": 0.8375,
      "trend": "flat"
    },
    {
      "date": "2026-06-04",
      "yhat": 2.3393,
      "yhat_lower": 2.1603,
      "yhat_upper": 2.5182,
      "confidence": 0.8375,
      "trend": "flat"
    },
    {
      "date": "2026-06-05",
      "yhat": 2.3275,
      "yhat_lower": 2.1494,
      "yhat_upper": 2.5055,
      "confidence": 0.8375,
      "trend": "flat"
    },
    {
      "date": "2026-06-06",
      "yhat": 2.3214,
      "yhat_lower": 2.1438,
      "yhat_upper": 2.499,
      "confidence": 0.8375,
      "trend": "flat"
    },
    {
      "date": "2026-06-07",
      "yhat": 2.316,
      "yhat_lower": 2.1389,
      "yhat_upper": 2.4932,
      "confidence": 0.8375,
      "trend": "flat"
    },
    {
      "date": "2026-06-08",
      "yhat": 2.3228,
      "yhat_lower": 2.1451,
      "yhat_upper": 2.5005,
      "confidence": 0.8375,
      "trend": "flat"
    },
    {
      "date": "2026-06-09",
      "yhat": 2.3162,
      "yhat_lower": 2.139,
      "yhat_upper": 2.4934,
      "confidence": 0.8375,
      "trend": "flat"
    },
    {
      "date": "2026-06-10",
      "yhat": 2.3278,
      "yhat_lower": 2.1498,
      "yhat_upper": 2.5059,
      "confidence": 0.8375,
      "trend": "flat"
    },
    {
      "date": "2026-06-11",
      "yhat": 2.3218,
      "yhat_lower": 2.1442,
      "yhat_upper": 2.4994,
      "confidence": 0.8375,
      "trend": "flat"
    },
    {
      "date": "2026-06-12",
      "yhat": 2.31,
      "yhat_lower": 2.1333,
      "yhat_upper": 2.4867,
      "confidence": 0.8375,
      "trend": "flat"
    },
    {
      "date": "2026-06-13",
      "yhat": 2.3039,
      "yhat_lower": 2.1277,
      "yhat_upper": 2.4802,
      "confidence": 0.8375,
      "trend": "flat"
    },
    {
      "date": "2026-06-14",
      "yhat": 2.2986,
      "yhat_lower": 2.1227,
      "yhat_upper": 2.4744,
      "confidence": 0.8375,
      "trend": "flat"
    },
    {
      "date": "2026-06-15",
      "yhat": 2.3054,
      "yhat_lower": 2.129,
      "yhat_upper": 2.4817,
      "confidence": 0.8375,
      "trend": "flat"
    },
    {
      "date": "2026-06-16",
      "yhat": 2.2988,
      "yhat_lower": 2.1229,
      "yhat_upper": 2.4746,
      "confidence": 0.8375,
      "trend": "flat"
    },
    {
      "date": "2026-06-17",
      "yhat": 2.3104,
      "yhat_lower": 2.1336,
      "yhat_upper": 2.4871,
      "confidence": 0.8375,
      "trend": "flat"
    },
    {
      "date": "2026-06-18",
      "yhat": 2.3043,
      "yhat_lower": 2.128,
      "yhat_upper": 2.4806,
      "confidence": 0.8375,
      "trend": "flat"
    },
    {
      "date": "2026-06-19",
      "yhat": 2.2925,
      "yhat_lower": 2.1171,
      "yhat_upper": 2.4679,
      "confidence": 0.8375,
      "trend": "flat"
    },
    {
      "date": "2026-06-20",
      "yhat": 2.2864,
      "yhat_lower": 2.1115,
      "yhat_upper": 2.4613,
      "confidence": 0.8375,
      "trend": "flat"
    },
    {
      "date": "2026-06-21",
      "yhat": 2.2811,
      "yhat_lower": 2.1066,
      "yhat_upper": 2.4556,
      "confidence": 0.8375,
      "trend": "flat"
    },
    {
      "date": "2026-06-22",
      "yhat": 2.2879,
      "yhat_lower": 2.1128,
      "yhat_upper": 2.4629,
      "confidence": 0.8375,
      "trend": "flat"
    },
    {
      "date": "2026-06-23",
      "yhat": 2.2813,
      "yhat_lower": 2.1068,
      "yhat_upper": 2.4558,
      "confidence": 0.8375,
      "trend": "flat"
    },
    {
      "date": "2026-06-24",
      "yhat": 2.2929,
      "yhat_lower": 2.1175,
      "yhat_upper": 2.4683,
      "confidence": 0.8375,
      "trend": "flat"
    }
  ]
}