{
  "version": "xfd-20260528021722",
  "forecast": [
    {
      "date": "2026-05-26",
      "yhat": 9.9386,
      "yhat_lower": 9.1793,
      "yhat_upper": 10.6979,
      "confidence": 0.84,
      "trend": "flat"
    },
    {
      "date": "2026-05-27",
      "yhat": 9.9122,
      "yhat_lower": 9.1549,
      "yhat_upper": 10.6695,
      "confidence": 0.84,
      "trend": "flat"
    },
    {
      "date": "2026-05-28",
      "yhat": 9.9601,
      "yhat_lower": 9.1992,
      "yhat_upper": 10.7211,
      "confidence": 0.84,
      "trend": "flat"
    },
    {
      "date": "2026-05-29",
      "yhat": 9.8956,
      "yhat_lower": 9.1396,
      "yhat_upper": 10.6516,
      "confidence": 0.84,
      "trend": "flat"
    },
    {
      "date": "2026-05-30",
      "yhat": 9.881,
      "yhat_lower": 9.1261,
      "yhat_upper": 10.6359,
      "confidence": 0.84,
      "trend": "flat"
    },
    {
      "date": "2026-05-31",
      "yhat": 9.9227,
      "yhat_lower": 9.1646,
      "yhat_upper": 10.6808,
      "confidence": 0.84,
      "trend": "flat"
    },
    {
      "date": "2026-06-01",
      "yhat": 9.9207,
      "yhat_lower": 9.1628,
      "yhat_upper": 10.6786,
      "confidence": 0.84,
      "trend": "flat"
    },
    {
      "date": "2026-06-02",
      "yhat": 9.9243,
      "yhat_lower": 9.1661,
      "yhat_upper": 10.6825,
      "confidence": 0.84,
      "trend": "flat"
    },
    {
      "date": "2026-06-03",
      "yhat": 9.8979,
      "yhat_lower": 9.1417,
      "yhat_upper": 10.6541,
      "confidence": 0.84,
      "trend": "flat"
    },
    {
      "date": "2026-06-04",
      "yhat": 9.9458,
      "yhat_lower": 9.186,
      "yhat_upper": 10.7057,
      "confidence": 0.84,
      "trend": "flat"
    },
    {
      "date": "2026-06-05",
      "yhat": 9.8813,
      "yhat_lower": 9.1264,
      "yhat_upper": 10.6362,
      "confidence": 0.84,
      "trend": "flat"
    },
    {
      "date": "2026-06-06",
      "yhat": 9.8667,
      "yhat_lower": 9.1129,
      "yhat_upper": 10.6206,
      "confidence": 0.84,
      "trend": "flat"
    },
    {
      "date": "2026-06-07",
      "yhat": 9.9085,
      "yhat_lower": 9.1514,
      "yhat_upper": 10.6655,
      "confidence": 0.84,
      "trend": "flat"
    },
    {
      "date": "2026-06-08",
      "yhat": 9.9064,
      "yhat_lower": 9.1496,
      "yhat_upper": 10.6633,
      "confidence": 0.84,
      "trend": "flat"
    },
    {
      "date": "2026-06-09",
      "yhat": 9.91,
      "yhat_lower": 9.1529,
      "yhat_upper": 10.6671,
      "confidence": 0.84,
      "trend": "flat"
    },
    {
      "date": "2026-06-10",
      "yhat": 9.8836,
      "yhat_lower": 9.1285,
      "yhat_upper": 10.6387,
      "confidence": 0.84,
      "trend": "flat"
    },
    {
      "date": "2026-06-11",
      "yhat": 9.9315,
      "yhat_lower": 9.1728,
      "yhat_upper": 10.6903,
      "confidence": 0.84,
      "trend": "flat"
    },
    {
      "date": "2026-06-12",
      "yhat": 9.867,
      "yhat_lower": 9.1132,
      "yhat_upper": 10.6208,
      "confidence": 0.84,
      "trend": "flat"
    },
    {
      "date": "2026-06-13",
      "yhat": 9.8525,
      "yhat_lower": 9.0997,
      "yhat_upper": 10.6052,
      "confidence": 0.84,
      "trend": "flat"
    },
    {
      "date": "2026-06-14",
      "yhat": 9.8942,
      "yhat_lower": 9.1383,
      "yhat_upper": 10.6501,
      "confidence": 0.84,
      "trend": "flat"
    },
    {
      "date": "2026-06-15",
      "yhat": 9.8921,
      "yhat_lower": 9.1364,
      "yhat_upper": 10.6479,
      "confidence": 0.84,
      "trend": "flat"
    },
    {
      "date": "2026-06-16",
      "yhat": 9.8957,
      "yhat_lower": 9.1397,
      "yhat_upper": 10.6517,
      "confidence": 0.84,
      "trend": "flat"
    },
    {
      "date": "2026-06-17",
      "yhat": 9.8693,
      "yhat_lower": 9.1153,
      "yhat_upper": 10.6233,
      "confidence": 0.84,
      "trend": "flat"
    },
    {
      "date": "2026-06-18",
      "yhat": 9.9173,
      "yhat_lower": 9.1596,
      "yhat_upper": 10.6749,
      "confidence": 0.84,
      "trend": "flat"
    },
    {
      "date": "2026-06-19",
      "yhat": 9.8527,
      "yhat_lower": 9.1,
      "yhat_upper": 10.6055,
      "confidence": 0.84,
      "trend": "flat"
    },
    {
      "date": "2026-06-20",
      "yhat": 9.8382,
      "yhat_lower": 9.0865,
      "yhat_upper": 10.5898,
      "confidence": 0.84,
      "trend": "flat"
    },
    {
      "date": "2026-06-21",
      "yhat": 9.8799,
      "yhat_lower": 9.1251,
      "yhat_upper": 10.6347,
      "confidence": 0.84,
      "trend": "flat"
    },
    {
      "date": "2026-06-22",
      "yhat": 9.8778,
      "yhat_lower": 9.1232,
      "yhat_upper": 10.6325,
      "confidence": 0.84,
      "trend": "flat"
    },
    {
      "date": "2026-06-23",
      "yhat": 9.8814,
      "yhat_lower": 9.1265,
      "yhat_upper": 10.6363,
      "confidence": 0.84,
      "trend": "flat"
    },
    {
      "date": "2026-06-24",
      "yhat": 9.855,
      "yhat_lower": 9.1021,
      "yhat_upper": 10.6079,
      "confidence": 0.84,
      "trend": "flat"
    }
  ]
}